noo/__init__.py
noo/__main__.py
noo/cli/__init__.py
noo/cli/components/__init__.py
noo/cli/components/collection.py
noo/cli/components/registry.py
noo/impl/__init__.py
noo/impl/core/__init__.py
noo/impl/core/core.py
noo/impl/core/formatter.py
noo/impl/core/resolver.py
noo/impl/core/runner.py
noo/impl/core/variables.py
noo/impl/models/__init__.py
noo/impl/models/actions.py
noo/impl/models/noofile.py
noo/impl/packager/__init__.py
noo/impl/packager/packager.py
noo/impl/packager/reader.py
noo/impl/packager/runners/__init__.py
noo/impl/packager/runners/base.py
noo/impl/packager/runners/javascript.py
noo/impl/packager/runners/python_poetry.py
noo/impl/resolvers/__init__.py
noo/impl/resolvers/github.py
noo/impl/resolvers/local.py
noo/impl/utils/__init__.py
noo/impl/utils/registry.py
pynoo-1.4.4.dist-info/entry_points.txt
pynoo-1.4.4.dist-info/LICENSE
pynoo-1.4.4.dist-info/WHEEL
pynoo-1.4.4.dist-info/METADATA
pynoo-1.4.4.dist-info/RECORD
